Metadata-Version: 2.1
Name: Fiicen-py
Version: 1.3.1
Summary: FiicenというSNSに使えるAPIラッパー
Home-page: https://github.com/taka-4602/Fiicen-py
Author: taka4602
Author-email: shun4602@gmail.com
Keywords: fiicen
Classifier: Programming Language :: Python :: 3
Classifier: License :: OSI Approved :: MIT License
Classifier: Operating System :: OS Independent
Requires-Python: >=3.6
